cursofiap/__init__.py
cursofiap/core.py
henriquecomp_package-1.0.0.dist-info/METADATA
henriquecomp_package-1.0.0.dist-info/WHEEL
henriquecomp_package-1.0.0.dist-info/top_level.txt
henriquecomp_package-1.0.0.dist-info/RECORD
